lammpskit/__init__.py
lammpskit/config.py
lammpskit/ecellmodel/__init__.py
lammpskit/ecellmodel/data_processing.py
lammpskit/ecellmodel/filament_layer_analysis.py
lammpskit/io/__init__.py
lammpskit/io/lammps_readers.py
lammpskit/plotting/__init__.py
lammpskit/plotting/timeseries_plots.py
lammpskit/plotting/utils.py
lammpskit-1.2.1.dist-info/licenses/LICENSE
lammpskit-1.2.1.dist-info/METADATA
lammpskit-1.2.1.dist-info/WHEEL
lammpskit-1.2.1.dist-info/top_level.txt
lammpskit-1.2.1.dist-info/RECORD
