Metadata-Version: 2.4
Name: lammpskit
Version: 1.2.1
Summary: A Python toolkit for advanced LAMMPS data processing and scientific simulation analysis.
Home-page: https://github.com/simantalahkar/lammpskit
Author: Simanta Lahkar
Author-email: Simanta Lahkar <simantalahkar@hotmail.com>
License: GPL-3.0-or-later
Project-URL: Homepage, https://github.com/simantalahkar/lammpskit
Project-URL: Documentation, https://lammpskit.readthedocs.io/en/latest/
Project-URL: Source, https://github.com/simantalahkar/lammpskit
Project-URL: Bug Tracker, https://github.com/simantalahkar/lammpskit/issues
Project-URL: Changelog, https://github.com/simantalahkar/lammpskit/blob/main/CHANGELOG.md
Project-URL: Discussions, https://github.com/simantalahkar/lammpskit/discussions
Keywords: LAMMPS,molecular-dynamics,ReRAM,electrochemical,memory-devices,filament-analysis,HfTaO,materials-science
Classifier: Development Status :: 5 - Production/Stable
Classifier: Intended Audience :: Science/Research
Classifier: License :: OSI Approved :: GNU General Public License v3 or later (GPLv3+)
Classifier: Operating System :: OS Independent
Classifier: Programming Language :: Python :: 3
Classifier: Programming Language :: Python :: 3.12
Classifier: Programming Language :: Python :: 3.13
Classifier: Topic :: Scientific/Engineering :: Chemistry
Classifier: Topic :: Scientific/Engineering :: Physics
Classifier: Topic :: Scientific/Engineering :: Visualization
Requires-Python: >=3.12
License-File: LICENSE
Requires-Dist: numpy>=2.3.1
Requires-Dist: matplotlib>=3.10.3
Requires-Dist: ovito>=3.12.4
Provides-Extra: dev
Requires-Dist: pytest>=8.4.1; extra == "dev"
Requires-Dist: pytest-cov>=6.2.1; extra == "dev"
Requires-Dist: pytest-mpl>=0.17.0; extra == "dev"
Requires-Dist: coverage>=7.9.1; extra == "dev"
Requires-Dist: sphinx>=8.2.3; extra == "dev"
Requires-Dist: sphinx-autodoc-typehints>=3.2.0; extra == "dev"
Requires-Dist: sphinx-rtd-theme>=3.0.2; extra == "dev"
Requires-Dist: Jinja2>=3.1.6; extra == "dev"
Requires-Dist: MarkupSafe>=3.0.2; extra == "dev"
Requires-Dist: black>=25.1.0; extra == "dev"
Requires-Dist: isort>=5.13.0; extra == "dev"
Requires-Dist: flake8>=7.3.0; extra == "dev"
Requires-Dist: mypy>=1.8.0; extra == "dev"
Requires-Dist: build>=1.2.2.post1; extra == "dev"
Requires-Dist: setuptools>=80.9.0; extra == "dev"
Requires-Dist: wheel>=0.45.1; extra == "dev"
Requires-Dist: twine>=6.1.0; extra == "dev"
Requires-Dist: readme_renderer>=44.0; extra == "dev"
Requires-Dist: pillow>=11.2.1; extra == "dev"
Requires-Dist: packaging>=25.0; extra == "dev"
Requires-Dist: cycler>=0.12.1; extra == "dev"
Requires-Dist: fonttools>=4.58.4; extra == "dev"
Requires-Dist: pluggy>=1.6.0; extra == "dev"
Requires-Dist: pyparsing>=3.2.3; extra == "dev"
Requires-Dist: python-dateutil>=2.9.0.post0; extra == "dev"
Requires-Dist: requests>=2.32.4; extra == "dev"
Requires-Dist: requests-toolbelt>=1.0.0; extra == "dev"
Requires-Dist: rich>=14.0.0; extra == "dev"
Dynamic: author
Dynamic: home-page
Dynamic: license-file
Dynamic: requires-python
